pycob/__init__.py
pycob/advanced.py
pycob/all_components.py
pycob/app.py
pycob/auth_forms.py
pycob/component_interface.py
pycob/generated.py
pycob/handler.py
pycob/request.py
pycob/spec.json
pycob/user.py
pycob/deploy/__main__.py
pycob-0.1.31.dist-info/METADATA
pycob-0.1.31.dist-info/WHEEL
pycob-0.1.31.dist-info/licenses/LICENSE
pycob-0.1.31.dist-info/RECORD
