Metadata-Version: 2.1
Name: pycob
Version: 0.1.31
Summary: Build web apps using just Python
Project-URL: Homepage, https://www.pycob.com/
Project-URL: Bug Tracker, https://github.com/pycob/pycob/issues
Author-email: Zain Hoda <zain@pycob.com>
License-File: LICENSE
Keywords: crud,framework,pycob,python,web
Classifier: License :: OSI Approved :: MIT License
Classifier: Operating System :: OS Independent
Classifier: Programming Language :: Python :: 3
Requires-Python: >=3.7
Requires-Dist: dataclasses-json
Requires-Dist: flask
Requires-Dist: gitignore-parser
Requires-Dist: requests
Requires-Dist: sqlalchemy
